google_reverse_image_search/__init__.py
google_reverse_image_search/google_reverse_search.py
google_reverse_image_search-0.5.0.dist-info/LICENSE
google_reverse_image_search-0.5.0.dist-info/METADATA
google_reverse_image_search-0.5.0.dist-info/WHEEL
google_reverse_image_search-0.5.0.dist-info/top_level.txt
google_reverse_image_search-0.5.0.dist-info/RECORD
