Metadata-Version: 2.1
Name: google-reverse-image-search
Version: 0.5.0
Summary: A package to scrape Google Images for image relating to a picture or query
Author-email: horse-3903 <horse3903410@gmail.com>
Project-URL: Homepage, https://github.com/horse-3903/google-reverse-image-search
Project-URL: Bug Tracker, https://github.com/horse-3903/google-reverse-image-search/issues
Classifier: Programming Language :: Python :: 3
Classifier: License :: OSI Approved :: MIT License
Classifier: Operating System :: OS Independent
Requires-Python: >=3.9
License-File: LICENSE
Requires-Dist: playwright (<=1.29.1)
Requires-Dist: validators (<=0.20.0)
